netmind/__init__.py
netmind/client.py
netmind/constants.py
netmind/exceptions.py
netmind/resources/__init__.py
netmind/resources/chat.py
netmind/resources/code_interpreter.py
netmind/resources/embeddings.py
netmind/resources/files.py
netmind/resources/parse_pro.py
netmind/types/__init__.py
netmind/types/abstract.py
netmind/types/code_interpreter.py
netmind/types/files.py
netmind/types/parse_pro.py
netmind/version.py
netmind-0.1.11.dist-info/LICENSE
netmind-0.1.11.dist-info/METADATA
netmind-0.1.11.dist-info/WHEEL
netmind-0.1.11.dist-info/RECORD
