Metadata-Version: 2.3
Name: netmind
Version: 0.1.11
Summary: The official Python library for the NetMind's API
License: MIT
Author: yanrujing
Author-email: rujing.yan@protagonist-ai.com
Requires-Python: >=3.10
Classifier: License :: OSI Approved :: MIT License
Classifier: Programming Language :: Python :: 3
Classifier: Programming Language :: Python :: 3.10
Classifier: Programming Language :: Python :: 3.11
Classifier: Programming Language :: Python :: 3.12
Classifier: Programming Language :: Python :: 3.13
Requires-Dist: filetype (>=1.2.0,<2.0.0)
Requires-Dist: openai (>=1.86.0,<2.0.0)
Project-URL: Bug Tracker, https://github.com/protagolabs/netmind-python/issues
Project-URL: Homepage, https://github.com/protagolabs/netmind-python
